plone.registry-2.0.2-py3.13-nspkg.pth
plone/registry/__init__.py
plone/registry/configure.zcml
plone/registry/events.py
plone/registry/events.rst
plone/registry/field.py
plone/registry/field.rst
plone/registry/fieldfactory.py
plone/registry/fieldref.py
plone/registry/interfaces.py
plone/registry/record.py
plone/registry/recordsproxy.py
plone/registry/registry.py
plone/registry/registry.rst
plone/registry/tests.py
plone_registry-2.0.2.dist-info/METADATA
plone_registry-2.0.2.dist-info/WHEEL
plone_registry-2.0.2.dist-info/namespace_packages.txt
plone_registry-2.0.2.dist-info/top_level.txt
plone_registry-2.0.2.dist-info/RECORD
