Metadata-Version: 2.4
Name: plone.registry
Version: 2.0.2
Summary: Registry for application settings (like debconf/ about:config)
Home-page: https://pypi.org/project/plone.registry
Author: Martin Aspeli, Wichert Akkerman, Hanno Schlichting
Author-email: plone-developers@lists.sourceforge.net
License: GPL
Keywords: configuration registry
Classifier: Development Status :: 5 - Production/Stable
Classifier: Framework :: Plone
Classifier: Framework :: Plone :: 6.0
Classifier: Framework :: Plone :: Core
Classifier: License :: OSI Approved :: GNU General Public License (GPL)
Classifier: Programming Language :: Python
Classifier: Programming Language :: Python :: 3
Classifier: Programming Language :: Python :: 3.8
Classifier: Programming Language :: Python :: 3.9
Classifier: Programming Language :: Python :: 3.10
Classifier: Programming Language :: Python :: 3.11
Classifier: Topic :: Software Development :: Libraries :: Python Modules
Requires-Python: >=3.8
Requires-Dist: setuptools
Requires-Dist: Zope
Provides-Extra: test
Requires-Dist: plone.schema; extra == "test"
Dynamic: author
Dynamic: author-email
Dynamic: classifier
Dynamic: description
Dynamic: home-page
Dynamic: keywords
Dynamic: license
Dynamic: provides-extra
Dynamic: requires-dist
Dynamic: requires-python
Dynamic: summary
